[
{
    "model": "catalog.product",
    "pk": 1,
    "fields": {
        "name": "Машина",
        "description": "Самая быстрая и красивая в мире",
        "image": "catalog/image/машина.jpg",
        "category": 1,
        "price": 1000000,
        "created_at": "2024-09-10T17:17:27.933Z",
        "updated_at": "2024-09-10T17:17:27.933Z"
    }
},
{
    "model": "catalog.category",
    "pk": 1,
    "fields": {
        "name": "Cars",
        "description": "Разные машины мира"
    }
},
{
    "model": "catalog.category",
    "pk": 2,
    "fields": {
        "name": "Houses",
        "description": "Разные дома мира"
    }
},
{
    "model": "catalog.category",
    "pk": 3,
    "fields": {
        "name": "Countries",
        "description": "Разные страны мира"
    }
}
]
